imdb/imdb.py
imdb/init.py
tdm_drward-0.0.1.dist-info/LICENSE
tdm_drward-0.0.1.dist-info/METADATA
tdm_drward-0.0.1.dist-info/WHEEL
tdm_drward-0.0.1.dist-info/top_level.txt
tdm_drward-0.0.1.dist-info/RECORD
