Metadata-Version: 2.1
Name: tdm-drward
Version: 0.0.1
Summary: Find rating from imdb
Author-email: Yuke Zhang <zhan3447@purdue.edu>
License: MIT License        
Keywords: example,imdb,tutorial,rating
Classifier: License :: OSI Approved :: MIT License
Classifier: Programming Language :: Python
Classifier: Programming Language :: Python :: 3
Requires-Python: >=3.10
License-File: LICENSE
Requires-Dist: lxml (>=4.9.1)
Requires-Dist: requests (>=2.28.1)
